visits/__init__.py
visits/__main__.py
visits-0.0.4.dist-info/LICENSE
visits-0.0.4.dist-info/METADATA
visits-0.0.4.dist-info/WHEEL
visits-0.0.4.dist-info/top_level.txt
visits-0.0.4.dist-info/RECORD
